{
  "headline": {
    "before": "Work with me to ",
    "highlight": "achieve results"
  },
  "stats": {
    "startups": {
      "value": "+16",
      "label": "Startups I worked with"
    },
    "timeToResults": {
      "value": "3-6 months",
      "label": "Average time to results"
    },
    "funds": {
      "value": "€13M+",
      "label": "Raised by the startups I worked with"
    }
  },
  "caseStudies": {
    "talentware": {
      "name": "Talentware",
      "description": "Talentware is the talent management platform designed to help businesses effectively engage, develop, and retain talent through a skill-based approach.",
      "achievements": [
        {
          "text": "Assembled a robust team, ",
          "highlight": "ensuring agility and innovation."
        },
        {
          "text": "In just three months, we've already got customers signing up and managed to bag ",
          "highlight": "€800k in pre-seed",
          "textAfter": " funds."
        },
        {
          "text": "Formulated a strategic product and ",
          "highlight": "technical roadmap",
          "textAfter": ", targeting short-to-medium-term goals."
        }
      ]
    },
    "pausetiv": {
      "name": "Pausetiv",
      "description": "Pausetiv is a platform that helps women discover and manage menopause with a structured medical approach, connecting patients and healthcare professionals.",
      "achievements": [
        {
          "text": "From zero to live ",
          "highlight": "in just 4 months",
          "textAfter": " with a freelance team built from scratch."
        },
        {
          "text": "A ",
          "highlight": "medical-grade platform",
          "textAfter": " with polished interface from day zero."
        },
        {
          "text": "First ",
          "highlight": "B2B partnerships",
          "textAfter": " with companies for welfare benefits."
        }
      ]
    },
    "lexroom": {
      "name": "Lexroom.ai",
      "description": "Lexroom.ai is an AI-powered legal research tool that quickly provides relevant legal sources and drafts opinions based on user queries.",
      "achievements": [
        {
          "text": "Assembled a ",
          "highlight": "talented team quickly",
          "textAfter": ", setting the stage for rapid progress."
        },
        {
          "text": "Significant early achievements, including a successful ",
          "highlight": "€500k pre-seed funding round",
          "textAfter": " in January 2024."
        },
        {
          "text": "Led the development of the MVP, preparing for ",
          "highlight": "future growth."
        }
      ]
    }
  },
  "cta": {
    "label": "See my other experiences",
    "href": "/en/case-studies/"
  }
}
